math_package_tamar/__init__.py
math_package_tamar/basic_math.py
basic_math_package_tsommer-0.1.0.dist-info/LICENSE.txt
basic_math_package_tsommer-0.1.0.dist-info/METADATA
basic_math_package_tsommer-0.1.0.dist-info/WHEEL
basic_math_package_tsommer-0.1.0.dist-info/top_level.txt
basic_math_package_tsommer-0.1.0.dist-info/RECORD
