Metadata-Version: 2.1
Name: basic_math_package_tsommer
Version: 0.1.0
Summary: A basic math package
Author: TAMAR
Author-email: tzirw@example.com
Classifier: Programming Language :: Python :: 3
Classifier: License :: OSI Approved :: MIT License
Classifier: Operating System :: OS Independent
License-File: LICENSE.txt
